justice/__init__.py
justice/cli.py
justice/justice.py
justice/parser/__init__.py
justice/parser/line_parser/__init__.py
justice/parser/line_parser/abc.py
justice/parser/line_parser/company_name.py
justice/parser/line_parser/empty.py
justice-0.1.8.dist-info/AUTHORS.rst
justice-0.1.8.dist-info/LICENSE
justice-0.1.8.dist-info/METADATA
justice-0.1.8.dist-info/WHEEL
justice-0.1.8.dist-info/entry_points.txt
justice-0.1.8.dist-info/top_level.txt
justice-0.1.8.dist-info/RECORD
