Metadata-Version: 2.1
Name: justice
Version: 0.1.8
Summary: A python package to download company information from https://justice.cz/
Home-page: https://github.com/SukiCZ/justice
Author: Jakub Boukal
Author-email: www.bagr@gmail.com
License: MIT license
Keywords: justice
Platform: UNKNOWN
Classifier: Development Status :: 2 - Pre-Alpha
Classifier: Intended Audience :: Developers
Classifier: License :: OSI Approved :: MIT License
Classifier: Natural Language :: English
Classifier: Programming Language :: Python :: 3
Classifier: Programming Language :: Python :: 3.6
Classifier: Programming Language :: Python :: 3.7
Classifier: Programming Language :: Python :: 3.8
Classifier: Programming Language :: Python :: 3.9
Requires-Python: >=3.6
Requires-Dist: dateparser (<2,>=1.0.0)
Requires-Dist: pyquery (<2,>=1.4.3)
